fly/__init__.py
fly/cli.py
fly/command.py
fly/config.py
fly/constant.py
fly/context.py
fly/debug.py
fly/exception.py
fly/fly.py
fly/handle.py
fly/middleware/__init__.py
fly/middleware/builtin.py
fly/middleware/core.py
fly/middleware/exception.py
fly/middleware/extra.py
fly/openapi.py
fly/request.py
fly/response.py
fly/route.py
fly/schema.py
fly/sdk.py
fly/session.py
fly/signal/__init__.py
fly/signal/builtin.py
fly/signal/core.py
fly/signal/exception.py
fly/static/swagger.html
fly/testclient.py
fly/utils/__init__.py
fly/utils/encrypt.py
fly/utils/func.py
fly/utils/kls.py
fly/utils/logger.py
fly/utils/remote.py
fly/utils/state.py
fly/view.py
fly_web-0.1.2.dist-info/METADATA
fly_web-0.1.2.dist-info/WHEEL
fly_web-0.1.2.dist-info/entry_points.txt
fly_web-0.1.2.dist-info/RECORD
