Metadata-Version: 2.1
Name: fly-web
Version: 0.1.2
Summary: A simple asgi web framework
Author: wanglei
Author-email: llggg2323@163.com
Requires-Python: >=3.11,<4.0
Classifier: Programming Language :: Python :: 3
Classifier: Programming Language :: Python :: 3.11
Classifier: Programming Language :: Python :: 3.12
Requires-Dist: apispec (>=6.4.0,<7.0.0)
Requires-Dist: loguru (>=0.7.2,<0.8.0)
Requires-Dist: pydantic (>=2.5.3,<3.0.0)
Requires-Dist: pyinstrument (>=4.6.1,<5.0.0)
Requires-Dist: pyjwt (>=2.8.0,<3.0.0)
Requires-Dist: pytest-asyncio (>=0.23.4,<0.24.0)
Requires-Dist: uvicorn (>=0.25.0,<0.26.0)
Requires-Dist: watchdog (>=3.0.0,<4.0.0)
